pythonanywhere_tools/__init__.py
pythonanywhere_tools/__main__.py
pythonanywhere_tools-0.1.2.dist-info/licenses/AUTHORS.rst
pythonanywhere_tools-0.1.2.dist-info/licenses/LICENSE
pythonanywhere_tools-0.1.2.dist-info/METADATA
pythonanywhere_tools-0.1.2.dist-info/WHEEL
pythonanywhere_tools-0.1.2.dist-info/top_level.txt
pythonanywhere_tools-0.1.2.dist-info/RECORD
