Metadata-Version: 2.4
Name: pythonanywhere-tools
Version: 0.1.2
Summary: Simple set of tools to, reload the webserver, or extend for 3 months the free tier programatically.
Author-email: Manuel Seromenho <manuelseromenho@gmail.com>
License-Expression: MIT
Project-URL: Homepage, https://github.com/manuelseromenho/pythonanywhere_tools
Requires-Python: >=3.10
License-File: LICENSE
License-File: AUTHORS.rst
Requires-Dist: requests
Requires-Dist: python-dotenv
Dynamic: license-file
